__init__.py
download_yt.py
gen_clip.py
logger.py
main.py
process_vid.py
processor.py
settings.py
stream_manager.py
stream_monitor.py
transcription.py
uploader.py
utils.py
autovod-1.1.0.dist-info/licenses/LICENSE
autovod-1.1.0.dist-info/METADATA
autovod-1.1.0.dist-info/WHEEL
autovod-1.1.0.dist-info/entry_points.txt
autovod-1.1.0.dist-info/top_level.txt
autovod-1.1.0.dist-info/RECORD
