Metadata-Version: 2.4
Name: autovod
Version: 1.1.0
Summary: Automatically download livestreams, clip with AI, and upload in realtime
Author-email: 0jc1 <52017130+0jc1@users.noreply.github.com>
License-Expression: MIT
Project-URL: Repository, https://github.com/0jc1/py-autovod
Project-URL: Issues, https://github.com/0jc1/py-autovod/issues
Project-URL: Documentation, https://github.com/0jc1/py-autovod#readme
Project-URL: Changelog, https://github.com/0jc1/py-autovod/releases
Keywords: livestream,kick,autovod,automation,ai,clipper,ffmpeg,streamlink,twitch,youtube
Classifier: Operating System :: OS Independent
Classifier: Programming Language :: Python :: 3
Classifier: Programming Language :: Python :: 3.10
Classifier: Programming Language :: Python :: 3.11
Classifier: Programming Language :: Python :: 3.12
Classifier: Topic :: Multimedia :: Video
Classifier: Topic :: Multimedia :: Video :: Capture
Classifier: Topic :: Internet
Requires-Python: >=3.10
License-File: LICENSE
Provides-Extra: dev
Requires-Dist: black; extra == "dev"
Requires-Dist: pytest; extra == "dev"
Requires-Dist: ruff; extra == "dev"
Requires-Dist: build; extra == "dev"
Dynamic: license-file
